kruksik_hello/__init__.py
kruksik_hello/main.py
kruksik_hello-0.0.3.dist-info/METADATA
kruksik_hello-0.0.3.dist-info/WHEEL
kruksik_hello-0.0.3.dist-info/entry_points.txt
kruksik_hello-0.0.3.dist-info/top_level.txt
kruksik_hello-0.0.3.dist-info/RECORD
